{
  "mint": "3M2ZpK3VBCGVsdagYs99xrEedi7PdKYe62NwFXx7pump",
  "symbol": "AGENT",
  "name": "Agent Safehouse",
  "creator_wallet": "HiSo5kykqDPs3EG14Fk9QY4B5RvkuEs8oJTiqPX3EDAn",
  "uri": "https://metadata.rapidlaunch.io/metadata/1c7bdcf7-013b-40b4-b968-0f395228cdcf.json",
  "pool": "pump",
  "bonding_curve_key": "85dPYeNMKEAQht2CPBBhRvCCzJFnnFJqHAbLMCUjRi93",
  "launch_signature": "2kkPC2HQbgyAyBq74fmFdhrmgNz5kLnQx8A7xdgebT6qLEn1cshSi3zd1uDD9pU212tAjm8CWgCtXXjeNwJzfk9D",
  "created_timestamp": null,
  "first_seen_at": "2026-03-09T05:22:56.442532",
  "last_seen_at": "2026-03-09T05:23:31.339864",
  "first_trade_at": "2026-03-09T05:22:57.088546",
  "last_trade_at": "2026-03-09T05:23:31.339864",
  "last_buy_at": "2026-03-09T05:23:25.557222",
  "last_sell_at": "2026-03-09T05:23:31.339864",
  "watchlisted_at": "2026-03-09T05:22:56.442599+00:00",
  "escalated_at": "2026-03-09T05:22:59.619706+00:00",
  "cooled_off_at": null,
  "inactive_at": null,
  "reawakened_at": null,
  "initial_buy": 66285714.255008,
  "launch_sol_amount": 1.975308641,
  "launch_market_cap_sol": 31.762049167045976,
  "current_market_cap_sol": 28.450696918552904,
  "peak_market_cap_sol": 57.541632161472585,
  "trough_market_cap_sol": 28.450696918552904,
  "peak_market_cap_at": "2026-03-09T05:23:03.408257",
  "trough_market_cap_at": "2026-03-09T05:23:31.339864",
  "total_trade_count": 73,
  "total_buy_count": 31,
  "total_sell_count": 42,
  "total_buy_sol": 16.408053363,
  "total_sell_sol": 20.886144944,
  "net_sol_flow": -4.478091581000001,
  "largest_buy_sol": 1.341839532,
  "largest_sell_sol": 1.512424864,
  "trades_last_1m": 73,
  "trades_last_5m": 73,
  "buys_last_1m": 31,
  "buys_last_5m": 31,
  "sells_last_1m": 42,
  "sells_last_5m": 42,
  "buy_sol_last_1m": 16.408053363,
  "buy_sol_last_5m": 16.408053363,
  "sell_sol_last_1m": 20.886144944,
  "sell_sol_last_5m": 20.886144944,
  "net_sol_flow_last_1m": -4.478091581000001,
  "net_sol_flow_last_5m": -4.478091581000001,
  "unique_traders": 26,
  "unique_buyers": 25,
  "unique_sellers": 24,
  "unique_traders_last_1m": 26,
  "unique_traders_last_5m": 26,
  "unique_buyers_last_1m": 25,
  "unique_buyers_last_5m": 25,
  "unique_sellers_last_1m": 24,
  "unique_sellers_last_5m": 24,
  "new_traders_last_1m": 26,
  "new_traders_last_5m": 26,
  "new_buyers_last_1m": 25,
  "new_buyers_last_5m": 25,
  "repeat_wallet_ratio": 0.9726,
  "repeat_buyer_ratio": 0.3871,
  "buyer_overlap_ratio": 0.0,
  "participant_churn_ratio": 1.0,
  "cluster_entropy": 0.9752,
  "participant_concentration_score": 0.0066,
  "wallet_novelty_score": 1.0,
  "new_buyer_velocity": 1.0,
  "participant_quality_score_v2": 0.6898,
  "status": "watching",
  "status_reason": "meets_watch_thresholds",
  "was_ever_watchlisted": true,
  "was_ever_escalated": true,
  "revival_count": 0,
  "recent_trades": [
    {
      "captured_at_utc": "2026-03-09T05:22:57.088546",
      "tx_type": "buy",
      "sol_amount": 0.39839982,
      "trader_wallet": "97V26zCSXhBRSGsnfK4dTai8sd34UHQkA3G7jS9MG9BC",
      "market_cap_sol": 38.358471548669186
    },
    {
      "captured_at_utc": "2026-03-09T05:22:57.155191",
      "tx_type": "buy",
      "sol_amount": 0.23012964,
      "trader_wallet": "Hn9B5qcoHAQZg6YsjT6twgugzw1YTNF9qahC1n7UKBao",
      "market_cap_sol": 38.862543470236666
    },
    {
      "captured_at_utc": "2026-03-09T05:22:57.220826",
      "tx_type": "buy",
      "sol_amount": 0.068650664,
      "trader_wallet": "FMLcAFEKzwgNpau6B7Y2WR6sdWkcc5dZzHtNLPpfc9Sq",
      "market_cap_sol": 39.0135518794687
    },
    {
      "captured_at_utc": "2026-03-09T05:22:58.575381",
      "tx_type": "buy",
      "sol_amount": 0.955930346,
      "trader_wallet": "CbXTyckBsFpe6XDfqNj1AGh8AawSrCmL7mGqMbSaYUpH",
      "market_cap_sol": 41.146704122889744
    },
    {
      "captured_at_utc": "2026-03-09T05:22:58.642438",
      "tx_type": "buy",
      "sol_amount": 1.015445504,
      "trader_wallet": "54R5wnehXtEq7zoNDyRnjgvzVwANLrdovsxBfKRSp9SY",
      "market_cap_sol": 43.47485183093408
    },
    {
      "captured_at_utc": "2026-03-09T05:22:58.709047",
      "tx_type": "buy",
      "sol_amount": 0.961957483,
      "trader_wallet": "Cs2b1mgijieZ6e27cc7CKqQpbGG52M9ahBRgoghgAHps",
      "market_cap_sol": 45.739457857540884
    },
    {
      "captured_at_utc": "2026-03-09T05:22:59.281114",
      "tx_type": "sell",
      "sol_amount": 0.270702695,
      "trader_wallet": "Hn9B5qcoHAQZg6YsjT6twgugzw1YTNF9qahC1n7UKBao",
      "market_cap_sol": 45.09636609229593
    },
    {
      "captured_at_utc": "2026-03-09T05:22:59.619572",
      "tx_type": "sell",
      "sol_amount": 1.438204023,
      "trader_wallet": "HiSo5kykqDPs3EG14Fk9QY4B5RvkuEs8oJTiqPX3EDAn",
      "market_cap_sol": 41.756064691791416
    },
    {
      "captured_at_utc": "2026-03-09T05:22:59.691040",
      "tx_type": "sell",
      "sol_amount": 0.433474957,
      "trader_wallet": "97V26zCSXhBRSGsnfK4dTai8sd34UHQkA3G7jS9MG9BC",
      "market_cap_sol": 40.77450152222074
    },
    {
      "captured_at_utc": "2026-03-09T05:23:00.196120",
      "tx_type": "sell",
      "sol_amount": 0.061514178,
      "trader_wallet": "FMLcAFEKzwgNpau6B7Y2WR6sdWkcc5dZzHtNLPpfc9Sq",
      "market_cap_sol": 40.63615437507058
    },
    {
      "captured_at_utc": "2026-03-09T05:23:00.266480",
      "tx_type": "sell",
      "sol_amount": 0.01023206,
      "trader_wallet": "FMLcAFEKzwgNpau6B7Y2WR6sdWkcc5dZzHtNLPpfc9Sq",
      "market_cap_sol": 40.613164985675
    },
    {
      "captured_at_utc": "2026-03-09T05:23:00.399381",
      "tx_type": "buy",
      "sol_amount": 0.767749714,
      "trader_wallet": "DRhKAGMXSfrH97vkkfFFbkoFwVNzYAaaDJgS3Jh16G96",
      "market_cap_sol": 42.356212091339735
    },
    {
      "captured_at_utc": "2026-03-09T05:23:00.466717",
      "tx_type": "buy",
      "sol_amount": 0.791532437,
      "trader_wallet": "6ws5PfZCMPa8v2Habr91fvaypYyN66V9VnY5QRiuAj1K",
      "market_cap_sol": 44.19159568089038
    },
    {
      "captured_at_utc": "2026-03-09T05:23:00.534627",
      "tx_type": "buy",
      "sol_amount": 0.704228627,
      "trader_wallet": "BWwhW5M2Degae36QmG4R5ejGDWwv8oJ1URoEbiLFAD6X",
      "market_cap_sol": 45.85726473946387
    },
    {
      "captured_at_utc": "2026-03-09T05:23:00.601377",
      "tx_type": "buy",
      "sol_amount": 0.669822556,
      "trader_wallet": "9hMT2FHBtM6Z2ThEqTKgsDRJAYeyfzVEshsDMEFhHUJs",
      "market_cap_sol": 47.47014702832069
    },
    {
      "captured_at_utc": "2026-03-09T05:23:02.870168",
      "tx_type": "sell",
      "sol_amount": 1.512424864,
      "trader_wallet": "HiSo5kykqDPs3EG14Fk9QY4B5RvkuEs8oJTiqPX3EDAn",
      "market_cap_sol": 43.86793090042156
    },
    {
      "captured_at_utc": "2026-03-09T05:23:02.940231",
      "tx_type": "buy",
      "sol_amount": 1.341839532,
      "trader_wallet": "D4yrdUWHTf2wUWr7TZc3gZdMLsZ77y6RfHN4U28etf1j",
      "market_cap_sol": 47.056744768939076
    },
    {
      "captured_at_utc": "2026-03-09T05:23:03.007309",
      "tx_type": "buy",
      "sol_amount": 1.212134448,
      "trader_wallet": "6jb4os5q5gHpkXXimbPhWYCwn49Tq42uZWh3sBwxvwu4",
      "market_cap_sol": 50.03349253384094
    },
    {
      "captured_at_utc": "2026-03-09T05:23:03.075366",
      "tx_type": "buy",
      "sol_amount": 1.16741128,
      "trader_wallet": "BLzsHqVykVwSPhh2dU1QVnWpJqsWgfF4RqWnNhUiQiUc",
      "market_cap_sol": 52.98670683738791
    },
    {
      "captured_at_utc": "2026-03-09T05:23:03.143810",
      "tx_type": "buy",
      "sol_amount": 1.167503629,
      "trader_wallet": "6rLvfMMpewTpKs3qmeU85SFjp7tNzQik6U9Uts167siF",
      "market_cap_sol": 56.024840113884316
    },
    {
      "captured_at_utc": "2026-03-09T05:23:03.264981",
      "tx_type": "buy",
      "sol_amount": 0.560279498,
      "trader_wallet": "DDDD2zvzaPMLuZiC2Vos2i6TLFjJJ3bi1pN7kXQc3R5R",
      "market_cap_sol": 57.51289871804693
    },
    {
      "captured_at_utc": "2026-03-09T05:23:03.408257",
      "tx_type": "buy",
      "sol_amount": 0.010746853,
      "trader_wallet": "CoLABCacdPmEYPtiCkEaD5kED6tj9AD46caJsPnxgcYa",
      "market_cap_sol": 57.541632161472585
    },
    {
      "captured_at_utc": "2026-03-09T05:23:04.414092",
      "tx_type": "sell",
      "sol_amount": 0.520011705,
      "trader_wallet": "6ws5PfZCMPa8v2Habr91fvaypYyN66V9VnY5QRiuAj1K",
      "market_cap_sol": 56.159523949600164
    },
    {
      "captured_at_utc": "2026-03-09T05:23:04.481599",
      "tx_type": "sell",
      "sol_amount": 0.434779755,
      "trader_wallet": "BWwhW5M2Degae36QmG4R5ejGDWwv8oJ1URoEbiLFAD6X",
      "market_cap_sol": 55.01684472914194
    },
    {
      "captured_at_utc": "2026-03-09T05:23:04.549356",
      "tx_type": "sell",
      "sol_amount": 0.503118111,
      "trader_wallet": "DRhKAGMXSfrH97vkkfFFbkoFwVNzYAaaDJgS3Jh16G96",
      "market_cap_sol": 53.70921904936774
    },
    {
      "captured_at_utc": "2026-03-09T05:23:04.620036",
      "tx_type": "sell",
      "sol_amount": 0.381993496,
      "trader_wallet": "9hMT2FHBtM6Z2ThEqTKgsDRJAYeyfzVEshsDMEFhHUJs",
      "market_cap_sol": 52.726904945258795
    },
    {
      "captured_at_utc": "2026-03-09T05:23:07.279585",
      "tx_type": "sell",
      "sol_amount": 1.500497965,
      "trader_wallet": "D4yrdUWHTf2wUWr7TZc3gZdMLsZ77y6RfHN4U28etf1j",
      "market_cap_sol": 48.95605446350973
    },
    {
      "captured_at_utc": "2026-03-09T05:23:07.349360",
      "tx_type": "sell",
      "sol_amount": 1.18641987,
      "trader_wallet": "6jb4os5q5gHpkXXimbPhWYCwn49Tq42uZWh3sBwxvwu4",
      "market_cap_sol": 46.073534127582406
    },
    {
      "captured_at_utc": "2026-03-09T05:23:07.418211",
      "tx_type": "sell",
      "sol_amount": 1.017040135,
      "trader_wallet": "BLzsHqVykVwSPhh2dU1QVnWpJqsWgfF4RqWnNhUiQiUc",
      "market_cap_sol": 43.67215614678408
    },
    {
      "captured_at_utc": "2026-03-09T05:23:07.487777",
      "tx_type": "sell",
      "sol_amount": 0.913024905,
      "trader_wallet": "6rLvfMMpewTpKs3qmeU85SFjp7tNzQik6U9Uts167siF",
      "market_cap_sol": 41.57111670712614
    },
    {
      "captured_at_utc": "2026-03-09T05:23:07.711983",
      "tx_type": "sell",
      "sol_amount": 0.007764386,
      "trader_wallet": "CoLABCacdPmEYPtiCkEaD5kED6tj9AD46caJsPnxgcYa",
      "market_cap_sol": 41.553471516633266
    },
    {
      "captured_at_utc": "2026-03-09T05:23:07.938549",
      "tx_type": "buy",
      "sol_amount": 0.293333333,
      "trader_wallet": "BWEqoqpszS1XZG8sxjtcELRCLebXcW3h6N8cGHTQ4Zci",
      "market_cap_sol": 42.22269736979086
    },
    {
      "captured_at_utc": "2026-03-09T05:23:08.735449",
      "tx_type": "buy",
      "sol_amount": 0.048888888,
      "trader_wallet": "7puoa4VX92dUSDhKx6japTgakC9L9sToxdrhVYxwWYLu",
      "market_cap_sol": 42.33475476354077
    },
    {
      "captured_at_utc": "2026-03-09T05:23:08.874414",
      "tx_type": "sell",
      "sol_amount": 0.413181188,
      "trader_wallet": "DDDD2zvzaPMLuZiC2Vos2i6TLFjJJ3bi1pN7kXQc3R5R",
      "market_cap_sol": 41.392385093857136
    },
    {
      "captured_at_utc": "2026-03-09T05:23:09.771216",
      "tx_type": "buy",
      "sol_amount": 0.097777777,
      "trader_wallet": "C4QTccPPCYLn6YXaz2eLBZLtyMVdhVugiNdtYePPQWnz",
      "market_cap_sol": 41.61443529415562
    },
    {
      "captured_at_utc": "2026-03-09T05:23:09.988497",
      "tx_type": "buy",
      "sol_amount": 0.249101065,
      "trader_wallet": "DRhKAGMXSfrH97vkkfFFbkoFwVNzYAaaDJgS3Jh16G96",
      "market_cap_sol": 42.18282014392083
    },
    {
      "captured_at_utc": "2026-03-09T05:23:10.058244",
      "tx_type": "buy",
      "sol_amount": 0.24604072,
      "trader_wallet": "6ws5PfZCMPa8v2Habr91fvaypYyN66V9VnY5QRiuAj1K",
      "market_cap_sol": 42.74800663167763
    },
    {
      "captured_at_utc": "2026-03-09T05:23:10.127128",
      "tx_type": "buy",
      "sol_amount": 0.243357833,
      "trader_wallet": "BWwhW5M2Degae36QmG4R5ejGDWwv8oJ1URoEbiLFAD6X",
      "market_cap_sol": 43.31073006531071
    },
    {
      "captured_at_utc": "2026-03-09T05:23:10.196256",
      "tx_type": "buy",
      "sol_amount": 0.23927816,
      "trader_wallet": "9hMT2FHBtM6Z2ThEqTKgsDRJAYeyfzVEshsDMEFhHUJs",
      "market_cap_sol": 43.867607533383485
    },
    {
      "captured_at_utc": "2026-03-09T05:23:12.813342",
      "tx_type": "buy",
      "sol_amount": 0.463889902,
      "trader_wallet": "82qSmvML3zKUzrcBkT8TR5kaUmeKuvrLWU9c9xuExbGg",
      "market_cap_sol": 44.95736233436801
    },
    {
      "captured_at_utc": "2026-03-09T05:23:12.885024",
      "tx_type": "buy",
      "sol_amount": 0.445803193,
      "trader_wallet": "4wuudpdbJzUFpsu1MgwbGEWg93NQcb9Wxyoaya9i7FMF",
      "market_cap_sol": 46.017226886715925
    },
    {
      "captured_at_utc": "2026-03-09T05:23:12.955754",
      "tx_type": "buy",
      "sol_amount": 0.524822264,
      "trader_wallet": "79hbkFpa1s6kLP4TC8gwAiRNHqL3Cnu6bHR8uN7Zwbwe",
      "market_cap_sol": 47.28077848481695
    },
    {
      "captured_at_utc": "2026-03-09T05:23:13.026306",
      "tx_type": "buy",
      "sol_amount": 0.521040197,
      "trader_wallet": "3ixtZXbbJjNEq89GbeFu8vJMGDMNSePofNEf5kecVhsA",
      "market_cap_sol": 48.55215320147342
    },
    {
      "captured_at_utc": "2026-03-09T05:23:13.096015",
      "tx_type": "buy",
      "sol_amount": 0.574513524,
      "trader_wallet": "97V26zCSXhBRSGsnfK4dTai8sd34UHQkA3G7jS9MG9BC",
      "market_cap_sol": 49.97355957595875
    },
    {
      "captured_at_utc": "2026-03-09T05:23:13.315843",
      "tx_type": "buy",
      "sol_amount": 0.411770893,
      "trader_wallet": "Hn9B5qcoHAQZg6YsjT6twgugzw1YTNF9qahC1n7UKBao",
      "market_cap_sol": 51.00494014896962
    },
    {
      "captured_at_utc": "2026-03-09T05:23:14.674681",
      "tx_type": "sell",
      "sol_amount": 0.586284417,
      "trader_wallet": "97V26zCSXhBRSGsnfK4dTai8sd34UHQkA3G7jS9MG9BC",
      "market_cap_sol": 49.53962637421657
    },
    {
      "captured_at_utc": "2026-03-09T05:23:14.882752",
      "tx_type": "sell",
      "sol_amount": 0.582362781,
      "trader_wallet": "CbXTyckBsFpe6XDfqNj1AGh8AawSrCmL7mGqMbSaYUpH",
      "market_cap_sol": 48.10525651803429
    },
    {
      "captured_at_utc": "2026-03-09T05:23:15.116489",
      "tx_type": "sell",
      "sol_amount": 0.512111917,
      "trader_wallet": "Cs2b1mgijieZ6e27cc7CKqQpbGG52M9ahBRgoghgAHps",
      "market_cap_sol": 46.86132782300375
    },
    {
      "captured_at_utc": "2026-03-09T05:23:15.186649",
      "tx_type": "sell",
      "sol_amount": 0.554510093,
      "trader_wallet": "54R5wnehXtEq7zoNDyRnjgvzVwANLrdovsxBfKRSp9SY",
      "market_cap_sol": 45.53278702902883
    },
    {
      "captured_at_utc": "2026-03-09T05:23:16.499847",
      "tx_type": "sell",
      "sol_amount": 0.538899317,
      "trader_wallet": "54R5wnehXtEq7zoNDyRnjgvzVwANLrdovsxBfKRSp9SY",
      "market_cap_sol": 44.25995280104053
    },
    {
      "captured_at_utc": "2026-03-09T05:23:16.571053",
      "tx_type": "sell",
      "sol_amount": 0.520713658,
      "trader_wallet": "CbXTyckBsFpe6XDfqNj1AGh8AawSrCmL7mGqMbSaYUpH",
      "market_cap_sol": 43.047212120474875
    },
    {
      "captured_at_utc": "2026-03-09T05:23:16.643522",
      "tx_type": "sell",
      "sol_amount": 0.458588194,
      "trader_wallet": "Cs2b1mgijieZ6e27cc7CKqQpbGG52M9ahBRgoghgAHps",
      "market_cap_sol": 41.993112895988155
    },
    {
      "captured_at_utc": "2026-03-09T05:23:17.155831",
      "tx_type": "buy",
      "sol_amount": 6.917e-06,
      "trader_wallet": "Gh8KS37fXFoYrZqSTd9y8d6S6QgaxvGUrpzYau41dpUs",
      "market_cap_sol": 41.99312869659075
    },
    {
      "captured_at_utc": "2026-03-09T05:23:20.730792",
      "tx_type": "sell",
      "sol_amount": 0.723532971,
      "trader_wallet": "3ixtZXbbJjNEq89GbeFu8vJMGDMNSePofNEf5kecVhsA",
      "market_cap_sol": 40.35660427388593
    },
    {
      "captured_at_utc": "2026-03-09T05:23:20.803489",
      "tx_type": "sell",
      "sol_amount": 0.225614635,
      "trader_wallet": "79hbkFpa1s6kLP4TC8gwAiRNHqL3Cnu6bHR8uN7Zwbwe",
      "market_cap_sol": 39.85294980969328
    },
    {
      "captured_at_utc": "2026-03-09T05:23:20.876970",
      "tx_type": "sell",
      "sol_amount": 0.698474393,
      "trader_wallet": "4wuudpdbJzUFpsu1MgwbGEWg93NQcb9Wxyoaya9i7FMF",
      "market_cap_sol": 38.313750585798665
    },
    {
      "captured_at_utc": "2026-03-09T05:23:20.950295",
      "tx_type": "sell",
      "sol_amount": 0.756467561,
      "trader_wallet": "82qSmvML3zKUzrcBkT8TR5kaUmeKuvrLWU9c9xuExbGg",
      "market_cap_sol": 36.680945460466965
    },
    {
      "captured_at_utc": "2026-03-09T05:23:22.481705",
      "tx_type": "sell",
      "sol_amount": 0.205125639,
      "trader_wallet": "79hbkFpa1s6kLP4TC8gwAiRNHqL3Cnu6bHR8uN7Zwbwe",
      "market_cap_sol": 36.244317530721645
    },
    {
      "captured_at_utc": "2026-03-09T05:23:22.538649",
      "tx_type": "sell",
      "sol_amount": 0.625355502,
      "trader_wallet": "3ixtZXbbJjNEq89GbeFu8vJMGDMNSePofNEf5kecVhsA",
      "market_cap_sol": 34.9293272145638
    },
    {
      "captured_at_utc": "2026-03-09T05:23:22.595671",
      "tx_type": "sell",
      "sol_amount": 0.690317362,
      "trader_wallet": "82qSmvML3zKUzrcBkT8TR5kaUmeKuvrLWU9c9xuExbGg",
      "market_cap_sol": 33.505950569958266
    },
    {
      "captured_at_utc": "2026-03-09T05:23:22.652224",
      "tx_type": "sell",
      "sol_amount": 0.58818801,
      "trader_wallet": "4wuudpdbJzUFpsu1MgwbGEWg93NQcb9Wxyoaya9i7FMF",
      "market_cap_sol": 32.316517445360375
    },
    {
      "captured_at_utc": "2026-03-09T05:23:24.742004",
      "tx_type": "sell",
      "sol_amount": 0.224735991,
      "trader_wallet": "BWEqoqpszS1XZG8sxjtcELRCLebXcW3h6N8cGHTQ4Zci",
      "market_cap_sol": 31.86773204769647
    },
    {
      "captured_at_utc": "2026-03-09T05:23:25.557222",
      "tx_type": "buy",
      "sol_amount": 0.024666666,
      "trader_wallet": "C61P8QiqPAPDfzGTCFPUgnsgPYeiMQQ1cwLqZf1r637q",
      "market_cap_sol": 31.916836711518503
    },
    {
      "captured_at_utc": "2026-03-09T05:23:26.292570",
      "tx_type": "sell",
      "sol_amount": 0.200889534,
      "trader_wallet": "9hMT2FHBtM6Z2ThEqTKgsDRJAYeyfzVEshsDMEFhHUJs",
      "market_cap_sol": 31.518019718370912
    },
    {
      "captured_at_utc": "2026-03-09T05:23:26.350181",
      "tx_type": "sell",
      "sol_amount": 0.237763262,
      "trader_wallet": "DRhKAGMXSfrH97vkkfFFbkoFwVNzYAaaDJgS3Jh16G96",
      "market_cap_sol": 31.049238962048584
    },
    {
      "captured_at_utc": "2026-03-09T05:23:26.407441",
      "tx_type": "sell",
      "sol_amount": 0.207858901,
      "trader_wallet": "BWwhW5M2Degae36QmG4R5ejGDWwv8oJ1URoEbiLFAD6X",
      "market_cap_sol": 30.642295981429736
    },
    {
      "captured_at_utc": "2026-03-09T05:23:26.464433",
      "tx_type": "sell",
      "sol_amount": 0.227267486,
      "trader_wallet": "6ws5PfZCMPa8v2Habr91fvaypYyN66V9VnY5QRiuAj1K",
      "market_cap_sol": 30.20042724436877
    },
    {
      "captured_at_utc": "2026-03-09T05:23:28.926292",
      "tx_type": "sell",
      "sol_amount": 0.070987374,
      "trader_wallet": "C4QTccPPCYLn6YXaz2eLBZLtyMVdhVugiNdtYePPQWnz",
      "market_cap_sol": 30.06306654494533
    },
    {
      "captured_at_utc": "2026-03-09T05:23:29.305861",
      "tx_type": "sell",
      "sol_amount": 0.023234522,
      "trader_wallet": "C61P8QiqPAPDfzGTCFPUgnsgPYeiMQQ1cwLqZf1r637q",
      "market_cap_sol": 30.018175711198726
    },
    {
      "captured_at_utc": "2026-03-09T05:23:31.167070",
      "tx_type": "sell",
      "sol_amount": 0.188974834,
      "trader_wallet": "9hMT2FHBtM6Z2ThEqTKgsDRJAYeyfzVEshsDMEFhHUJs",
      "market_cap_sol": 29.65430799820505
    },
    {
      "captured_at_utc": "2026-03-09T05:23:31.224731",
      "tx_type": "sell",
      "sol_amount": 0.223754068,
      "trader_wallet": "DRhKAGMXSfrH97vkkfFFbkoFwVNzYAaaDJgS3Jh16G96",
      "market_cap_sol": 29.22634238016614
    },
    {
      "captured_at_utc": "2026-03-09T05:23:31.282371",
      "tx_type": "sell",
      "sol_amount": 0.195693874,
      "trader_wallet": "BWwhW5M2Degae36QmG4R5ejGDWwv8oJ1URoEbiLFAD6X",
      "market_cap_sol": 28.854596358494195
    },
    {
      "captured_at_utc": "2026-03-09T05:23:31.339864",
      "tx_type": "sell",
      "sol_amount": 0.214054355,
      "trader_wallet": "6ws5PfZCMPa8v2Habr91fvaypYyN66V9VnY5QRiuAj1K",
      "market_cap_sol": 28.450696918552904
    }
  ],
  "trader_wallets": [
    "3ixtZXbbJjNEq89GbeFu8vJMGDMNSePofNEf5kecVhsA",
    "4wuudpdbJzUFpsu1MgwbGEWg93NQcb9Wxyoaya9i7FMF",
    "54R5wnehXtEq7zoNDyRnjgvzVwANLrdovsxBfKRSp9SY",
    "6jb4os5q5gHpkXXimbPhWYCwn49Tq42uZWh3sBwxvwu4",
    "6rLvfMMpewTpKs3qmeU85SFjp7tNzQik6U9Uts167siF",
    "6ws5PfZCMPa8v2Habr91fvaypYyN66V9VnY5QRiuAj1K",
    "79hbkFpa1s6kLP4TC8gwAiRNHqL3Cnu6bHR8uN7Zwbwe",
    "7puoa4VX92dUSDhKx6japTgakC9L9sToxdrhVYxwWYLu",
    "82qSmvML3zKUzrcBkT8TR5kaUmeKuvrLWU9c9xuExbGg",
    "97V26zCSXhBRSGsnfK4dTai8sd34UHQkA3G7jS9MG9BC",
    "9hMT2FHBtM6Z2ThEqTKgsDRJAYeyfzVEshsDMEFhHUJs",
    "BLzsHqVykVwSPhh2dU1QVnWpJqsWgfF4RqWnNhUiQiUc",
    "BWEqoqpszS1XZG8sxjtcELRCLebXcW3h6N8cGHTQ4Zci",
    "BWwhW5M2Degae36QmG4R5ejGDWwv8oJ1URoEbiLFAD6X",
    "C4QTccPPCYLn6YXaz2eLBZLtyMVdhVugiNdtYePPQWnz",
    "C61P8QiqPAPDfzGTCFPUgnsgPYeiMQQ1cwLqZf1r637q",
    "CbXTyckBsFpe6XDfqNj1AGh8AawSrCmL7mGqMbSaYUpH",
    "CoLABCacdPmEYPtiCkEaD5kED6tj9AD46caJsPnxgcYa",
    "Cs2b1mgijieZ6e27cc7CKqQpbGG52M9ahBRgoghgAHps",
    "D4yrdUWHTf2wUWr7TZc3gZdMLsZ77y6RfHN4U28etf1j",
    "DDDD2zvzaPMLuZiC2Vos2i6TLFjJJ3bi1pN7kXQc3R5R",
    "DRhKAGMXSfrH97vkkfFFbkoFwVNzYAaaDJgS3Jh16G96",
    "FMLcAFEKzwgNpau6B7Y2WR6sdWkcc5dZzHtNLPpfc9Sq",
    "Gh8KS37fXFoYrZqSTd9y8d6S6QgaxvGUrpzYau41dpUs",
    "HiSo5kykqDPs3EG14Fk9QY4B5RvkuEs8oJTiqPX3EDAn",
    "Hn9B5qcoHAQZg6YsjT6twgugzw1YTNF9qahC1n7UKBao"
  ],
  "buyer_wallets": [
    "3ixtZXbbJjNEq89GbeFu8vJMGDMNSePofNEf5kecVhsA",
    "4wuudpdbJzUFpsu1MgwbGEWg93NQcb9Wxyoaya9i7FMF",
    "54R5wnehXtEq7zoNDyRnjgvzVwANLrdovsxBfKRSp9SY",
    "6jb4os5q5gHpkXXimbPhWYCwn49Tq42uZWh3sBwxvwu4",
    "6rLvfMMpewTpKs3qmeU85SFjp7tNzQik6U9Uts167siF",
    "6ws5PfZCMPa8v2Habr91fvaypYyN66V9VnY5QRiuAj1K",
    "79hbkFpa1s6kLP4TC8gwAiRNHqL3Cnu6bHR8uN7Zwbwe",
    "7puoa4VX92dUSDhKx6japTgakC9L9sToxdrhVYxwWYLu",
    "82qSmvML3zKUzrcBkT8TR5kaUmeKuvrLWU9c9xuExbGg",
    "97V26zCSXhBRSGsnfK4dTai8sd34UHQkA3G7jS9MG9BC",
    "9hMT2FHBtM6Z2ThEqTKgsDRJAYeyfzVEshsDMEFhHUJs",
    "BLzsHqVykVwSPhh2dU1QVnWpJqsWgfF4RqWnNhUiQiUc",
    "BWEqoqpszS1XZG8sxjtcELRCLebXcW3h6N8cGHTQ4Zci",
    "BWwhW5M2Degae36QmG4R5ejGDWwv8oJ1URoEbiLFAD6X",
    "C4QTccPPCYLn6YXaz2eLBZLtyMVdhVugiNdtYePPQWnz",
    "C61P8QiqPAPDfzGTCFPUgnsgPYeiMQQ1cwLqZf1r637q",
    "CbXTyckBsFpe6XDfqNj1AGh8AawSrCmL7mGqMbSaYUpH",
    "CoLABCacdPmEYPtiCkEaD5kED6tj9AD46caJsPnxgcYa",
    "Cs2b1mgijieZ6e27cc7CKqQpbGG52M9ahBRgoghgAHps",
    "D4yrdUWHTf2wUWr7TZc3gZdMLsZ77y6RfHN4U28etf1j",
    "DDDD2zvzaPMLuZiC2Vos2i6TLFjJJ3bi1pN7kXQc3R5R",
    "DRhKAGMXSfrH97vkkfFFbkoFwVNzYAaaDJgS3Jh16G96",
    "FMLcAFEKzwgNpau6B7Y2WR6sdWkcc5dZzHtNLPpfc9Sq",
    "Gh8KS37fXFoYrZqSTd9y8d6S6QgaxvGUrpzYau41dpUs",
    "Hn9B5qcoHAQZg6YsjT6twgugzw1YTNF9qahC1n7UKBao"
  ],
  "seller_wallets": [
    "3ixtZXbbJjNEq89GbeFu8vJMGDMNSePofNEf5kecVhsA",
    "4wuudpdbJzUFpsu1MgwbGEWg93NQcb9Wxyoaya9i7FMF",
    "54R5wnehXtEq7zoNDyRnjgvzVwANLrdovsxBfKRSp9SY",
    "6jb4os5q5gHpkXXimbPhWYCwn49Tq42uZWh3sBwxvwu4",
    "6rLvfMMpewTpKs3qmeU85SFjp7tNzQik6U9Uts167siF",
    "6ws5PfZCMPa8v2Habr91fvaypYyN66V9VnY5QRiuAj1K",
    "79hbkFpa1s6kLP4TC8gwAiRNHqL3Cnu6bHR8uN7Zwbwe",
    "82qSmvML3zKUzrcBkT8TR5kaUmeKuvrLWU9c9xuExbGg",
    "97V26zCSXhBRSGsnfK4dTai8sd34UHQkA3G7jS9MG9BC",
    "9hMT2FHBtM6Z2ThEqTKgsDRJAYeyfzVEshsDMEFhHUJs",
    "BLzsHqVykVwSPhh2dU1QVnWpJqsWgfF4RqWnNhUiQiUc",
    "BWEqoqpszS1XZG8sxjtcELRCLebXcW3h6N8cGHTQ4Zci",
    "BWwhW5M2Degae36QmG4R5ejGDWwv8oJ1URoEbiLFAD6X",
    "C4QTccPPCYLn6YXaz2eLBZLtyMVdhVugiNdtYePPQWnz",
    "C61P8QiqPAPDfzGTCFPUgnsgPYeiMQQ1cwLqZf1r637q",
    "CbXTyckBsFpe6XDfqNj1AGh8AawSrCmL7mGqMbSaYUpH",
    "CoLABCacdPmEYPtiCkEaD5kED6tj9AD46caJsPnxgcYa",
    "Cs2b1mgijieZ6e27cc7CKqQpbGG52M9ahBRgoghgAHps",
    "D4yrdUWHTf2wUWr7TZc3gZdMLsZ77y6RfHN4U28etf1j",
    "DDDD2zvzaPMLuZiC2Vos2i6TLFjJJ3bi1pN7kXQc3R5R",
    "DRhKAGMXSfrH97vkkfFFbkoFwVNzYAaaDJgS3Jh16G96",
    "FMLcAFEKzwgNpau6B7Y2WR6sdWkcc5dZzHtNLPpfc9Sq",
    "HiSo5kykqDPs3EG14Fk9QY4B5RvkuEs8oJTiqPX3EDAn",
    "Hn9B5qcoHAQZg6YsjT6twgugzw1YTNF9qahC1n7UKBao"
  ],
  "trader_trade_counts": {
    "97V26zCSXhBRSGsnfK4dTai8sd34UHQkA3G7jS9MG9BC": 4,
    "Hn9B5qcoHAQZg6YsjT6twgugzw1YTNF9qahC1n7UKBao": 3,
    "FMLcAFEKzwgNpau6B7Y2WR6sdWkcc5dZzHtNLPpfc9Sq": 3,
    "CbXTyckBsFpe6XDfqNj1AGh8AawSrCmL7mGqMbSaYUpH": 3,
    "54R5wnehXtEq7zoNDyRnjgvzVwANLrdovsxBfKRSp9SY": 3,
    "Cs2b1mgijieZ6e27cc7CKqQpbGG52M9ahBRgoghgAHps": 3,
    "HiSo5kykqDPs3EG14Fk9QY4B5RvkuEs8oJTiqPX3EDAn": 2,
    "DRhKAGMXSfrH97vkkfFFbkoFwVNzYAaaDJgS3Jh16G96": 5,
    "6ws5PfZCMPa8v2Habr91fvaypYyN66V9VnY5QRiuAj1K": 5,
    "BWwhW5M2Degae36QmG4R5ejGDWwv8oJ1URoEbiLFAD6X": 5,
    "9hMT2FHBtM6Z2ThEqTKgsDRJAYeyfzVEshsDMEFhHUJs": 5,
    "D4yrdUWHTf2wUWr7TZc3gZdMLsZ77y6RfHN4U28etf1j": 2,
    "6jb4os5q5gHpkXXimbPhWYCwn49Tq42uZWh3sBwxvwu4": 2,
    "BLzsHqVykVwSPhh2dU1QVnWpJqsWgfF4RqWnNhUiQiUc": 2,
    "6rLvfMMpewTpKs3qmeU85SFjp7tNzQik6U9Uts167siF": 2,
    "DDDD2zvzaPMLuZiC2Vos2i6TLFjJJ3bi1pN7kXQc3R5R": 2,
    "CoLABCacdPmEYPtiCkEaD5kED6tj9AD46caJsPnxgcYa": 2,
    "BWEqoqpszS1XZG8sxjtcELRCLebXcW3h6N8cGHTQ4Zci": 2,
    "7puoa4VX92dUSDhKx6japTgakC9L9sToxdrhVYxwWYLu": 1,
    "C4QTccPPCYLn6YXaz2eLBZLtyMVdhVugiNdtYePPQWnz": 2,
    "82qSmvML3zKUzrcBkT8TR5kaUmeKuvrLWU9c9xuExbGg": 3,
    "4wuudpdbJzUFpsu1MgwbGEWg93NQcb9Wxyoaya9i7FMF": 3,
    "79hbkFpa1s6kLP4TC8gwAiRNHqL3Cnu6bHR8uN7Zwbwe": 3,
    "3ixtZXbbJjNEq89GbeFu8vJMGDMNSePofNEf5kecVhsA": 3,
    "Gh8KS37fXFoYrZqSTd9y8d6S6QgaxvGUrpzYau41dpUs": 1,
    "C61P8QiqPAPDfzGTCFPUgnsgPYeiMQQ1cwLqZf1r637q": 2
  },
  "buyer_trade_counts": {
    "97V26zCSXhBRSGsnfK4dTai8sd34UHQkA3G7jS9MG9BC": 2,
    "Hn9B5qcoHAQZg6YsjT6twgugzw1YTNF9qahC1n7UKBao": 2,
    "FMLcAFEKzwgNpau6B7Y2WR6sdWkcc5dZzHtNLPpfc9Sq": 1,
    "CbXTyckBsFpe6XDfqNj1AGh8AawSrCmL7mGqMbSaYUpH": 1,
    "54R5wnehXtEq7zoNDyRnjgvzVwANLrdovsxBfKRSp9SY": 1,
    "Cs2b1mgijieZ6e27cc7CKqQpbGG52M9ahBRgoghgAHps": 1,
    "DRhKAGMXSfrH97vkkfFFbkoFwVNzYAaaDJgS3Jh16G96": 2,
    "6ws5PfZCMPa8v2Habr91fvaypYyN66V9VnY5QRiuAj1K": 2,
    "BWwhW5M2Degae36QmG4R5ejGDWwv8oJ1URoEbiLFAD6X": 2,
    "9hMT2FHBtM6Z2ThEqTKgsDRJAYeyfzVEshsDMEFhHUJs": 2,
    "D4yrdUWHTf2wUWr7TZc3gZdMLsZ77y6RfHN4U28etf1j": 1,
    "6jb4os5q5gHpkXXimbPhWYCwn49Tq42uZWh3sBwxvwu4": 1,
    "BLzsHqVykVwSPhh2dU1QVnWpJqsWgfF4RqWnNhUiQiUc": 1,
    "6rLvfMMpewTpKs3qmeU85SFjp7tNzQik6U9Uts167siF": 1,
    "DDDD2zvzaPMLuZiC2Vos2i6TLFjJJ3bi1pN7kXQc3R5R": 1,
    "CoLABCacdPmEYPtiCkEaD5kED6tj9AD46caJsPnxgcYa": 1,
    "BWEqoqpszS1XZG8sxjtcELRCLebXcW3h6N8cGHTQ4Zci": 1,
    "7puoa4VX92dUSDhKx6japTgakC9L9sToxdrhVYxwWYLu": 1,
    "C4QTccPPCYLn6YXaz2eLBZLtyMVdhVugiNdtYePPQWnz": 1,
    "82qSmvML3zKUzrcBkT8TR5kaUmeKuvrLWU9c9xuExbGg": 1,
    "4wuudpdbJzUFpsu1MgwbGEWg93NQcb9Wxyoaya9i7FMF": 1,
    "79hbkFpa1s6kLP4TC8gwAiRNHqL3Cnu6bHR8uN7Zwbwe": 1,
    "3ixtZXbbJjNEq89GbeFu8vJMGDMNSePofNEf5kecVhsA": 1,
    "Gh8KS37fXFoYrZqSTd9y8d6S6QgaxvGUrpzYau41dpUs": 1,
    "C61P8QiqPAPDfzGTCFPUgnsgPYeiMQQ1cwLqZf1r637q": 1
  }
}