{
  "mint": "4apiDmJh3pDWe5urdSobMwhUv5prU9kS9UNLLT8npump",
  "symbol": "唐",
  "name": "The Blowjob Incident",
  "creator_wallet": "Q6f8WRhFPCg3AooHa4c3pC9BAf67LuyXXfGgPW8Abwp",
  "uri": "https://meta.uxento.io/data/642f9959-9159-4dc6-8deb-ac10ee553931",
  "pool": "pump",
  "bonding_curve_key": "DmC9VE87iXZgLs4R8geveJqWBFQmuE8HRxM2NRRUq4F6",
  "launch_signature": "3AjCAfzK53uBawPuNJgkF3u6Zqp1ghgrGB26LQwCfJhcgs1cq7xWEZksuEzU3Yhm6nUvDZiYGWtkyufApiEG1U7J",
  "created_timestamp": null,
  "first_seen_at": "2026-03-17T05:49:22.827752",
  "last_seen_at": "2026-03-17T05:54:52.257984",
  "first_trade_at": "2026-03-17T05:54:35.540334",
  "last_trade_at": "2026-03-17T05:54:52.257984",
  "last_buy_at": null,
  "last_sell_at": "2026-03-17T05:54:52.257984",
  "watchlisted_at": "2026-03-17T05:49:22.827791+00:00",
  "escalated_at": null,
  "cooled_off_at": null,
  "inactive_at": null,
  "reawakened_at": null,
  "initial_buy": 10493887.4851,
  "launch_sol_amount": 0.296296295,
  "launch_market_cap_sol": 28.513997179075172,
  "current_market_cap_sol": 27.958993476234856,
  "peak_market_cap_sol": 28.513997179075172,
  "trough_market_cap_sol": 27.958993476234856,
  "peak_market_cap_at": "2026-03-17T05:49:22.827752",
  "trough_market_cap_at": "2026-03-17T05:54:52.257984",
  "total_trade_count": 2,
  "total_buy_count": 0,
  "total_sell_count": 2,
  "total_buy_sol": 0.0,
  "total_sell_sol": 0.402684564,
  "net_sol_flow": -0.402684564,
  "largest_buy_sol": 0.0,
  "largest_sell_sol": 0.202684564,
  "trades_last_1m": 2,
  "trades_last_5m": 2,
  "buys_last_1m": 0,
  "buys_last_5m": 0,
  "sells_last_1m": 2,
  "sells_last_5m": 2,
  "buy_sol_last_1m": 0,
  "buy_sol_last_5m": 0,
  "sell_sol_last_1m": 0.402684564,
  "sell_sol_last_5m": 0.402684564,
  "net_sol_flow_last_1m": -0.402684564,
  "net_sol_flow_last_5m": -0.402684564,
  "unique_traders": 2,
  "unique_buyers": 0,
  "unique_sellers": 2,
  "unique_traders_last_1m": 2,
  "unique_traders_last_5m": 2,
  "unique_buyers_last_1m": 0,
  "unique_buyers_last_5m": 0,
  "unique_sellers_last_1m": 2,
  "unique_sellers_last_5m": 2,
  "new_traders_last_1m": 2,
  "new_traders_last_5m": 2,
  "new_buyers_last_1m": 0,
  "new_buyers_last_5m": 0,
  "repeat_wallet_ratio": 0.0,
  "repeat_buyer_ratio": 0.0,
  "buyer_overlap_ratio": 0.0,
  "participant_churn_ratio": 1.0,
  "cluster_entropy": 1.0,
  "participant_concentration_score": 0.0,
  "wallet_novelty_score": 0.0,
  "new_buyer_velocity": 0.0,
  "participant_quality_score_v2": 0.68,
  "status": "watching",
  "status_reason": "meets_watch_thresholds",
  "was_ever_watchlisted": true,
  "was_ever_escalated": false,
  "revival_count": 0,
  "recent_trades": [
    {
      "captured_at_utc": "2026-03-17T05:54:35.540334",
      "tx_type": "sell",
      "sol_amount": 0.202684564,
      "effective_sol_amount": 0.202684564,
      "is_dust_trade": false,
      "trader_wallet": "3zMYeGpoRa2myjfR8qWZbXmPMEBdFqiZBq6cxYqd5J75",
      "market_cap_sol": 28.333022677750176
    },
    {
      "captured_at_utc": "2026-03-17T05:54:52.257984",
      "tx_type": "sell",
      "sol_amount": 0.2,
      "effective_sol_amount": 0.2,
      "is_dust_trade": false,
      "trader_wallet": "HDFT6THyh5RRovybvDfrwmyJ7Etqf4GRiG1V6iqubCnu",
      "market_cap_sol": 27.958993476234856
    }
  ],
  "trader_wallets": [
    "3zMYeGpoRa2myjfR8qWZbXmPMEBdFqiZBq6cxYqd5J75",
    "HDFT6THyh5RRovybvDfrwmyJ7Etqf4GRiG1V6iqubCnu"
  ],
  "buyer_wallets": [],
  "seller_wallets": [
    "3zMYeGpoRa2myjfR8qWZbXmPMEBdFqiZBq6cxYqd5J75",
    "HDFT6THyh5RRovybvDfrwmyJ7Etqf4GRiG1V6iqubCnu"
  ],
  "trader_trade_counts": {
    "3zMYeGpoRa2myjfR8qWZbXmPMEBdFqiZBq6cxYqd5J75": 1,
    "HDFT6THyh5RRovybvDfrwmyJ7Etqf4GRiG1V6iqubCnu": 1
  },
  "buyer_trade_counts": {}
}