{
  "mint": "8PiXjmU9SWYsDrPnCCy9DSuqiwS8F8CQ56pgyiJtpump",
  "symbol": "PROSUMER",
  "name": "BONDED FEES ARNT WORKING",
  "creator_wallet": "HzDDmmMemd7g1EDMB7NYQw4e54YLxcY5D9ddPz6NqWQz",
  "uri": "https://metadata.j7tracker.com/metadata/8e7fec2b938d4aa2.json",
  "pool": "pump",
  "bonding_curve_key": "AJGaMArKJwik3gbFeemqwbgdcLbjixPnvg1B64vfmGWs",
  "launch_signature": "4PWqbcxMuFfszdwSTUgKPYDQn5V7A2vfqEZTvEKkk2ykLW3dLHJipEqR73Bas9nG9qPEw2LQt4jpeAeXrkYP4vT",
  "created_timestamp": null,
  "first_seen_at": "2026-03-17T06:28:53.054231",
  "last_seen_at": "2026-03-17T06:28:53.054231",
  "first_trade_at": null,
  "last_trade_at": null,
  "last_buy_at": null,
  "last_sell_at": null,
  "watchlisted_at": "2026-03-17T06:28:53.054282+00:00",
  "escalated_at": null,
  "cooled_off_at": null,
  "inactive_at": null,
  "reawakened_at": null,
  "initial_buy": 3576.654744,
  "launch_sol_amount": 0.0001,
  "launch_market_cap_sol": 27.959179869835328,
  "current_market_cap_sol": 27.959179869835328,
  "peak_market_cap_sol": 27.959179869835328,
  "trough_market_cap_sol": 27.959179869835328,
  "peak_market_cap_at": "2026-03-17T06:28:53.054231",
  "trough_market_cap_at": "2026-03-17T06:28:53.054231",
  "total_trade_count": 0,
  "total_buy_count": 0,
  "total_sell_count": 0,
  "total_buy_sol": 0.0,
  "total_sell_sol": 0.0,
  "net_sol_flow": 0.0,
  "largest_buy_sol": 0.0,
  "largest_sell_sol": 0.0,
  "trades_last_1m": 0,
  "trades_last_5m": 0,
  "buys_last_1m": 0,
  "buys_last_5m": 0,
  "sells_last_1m": 0,
  "sells_last_5m": 0,
  "buy_sol_last_1m": 0.0,
  "buy_sol_last_5m": 0.0,
  "sell_sol_last_1m": 0.0,
  "sell_sol_last_5m": 0.0,
  "net_sol_flow_last_1m": 0.0,
  "net_sol_flow_last_5m": 0.0,
  "unique_traders": 0,
  "unique_buyers": 0,
  "unique_sellers": 0,
  "unique_traders_last_1m": 0,
  "unique_traders_last_5m": 0,
  "unique_buyers_last_1m": 0,
  "unique_buyers_last_5m": 0,
  "unique_sellers_last_1m": 0,
  "unique_sellers_last_5m": 0,
  "new_traders_last_1m": 0,
  "new_traders_last_5m": 0,
  "new_buyers_last_1m": 0,
  "new_buyers_last_5m": 0,
  "repeat_wallet_ratio": 0.0,
  "repeat_buyer_ratio": 0.0,
  "buyer_overlap_ratio": 0.0,
  "participant_churn_ratio": 0.0,
  "cluster_entropy": 0.0,
  "participant_concentration_score": 0.0,
  "wallet_novelty_score": 0.0,
  "new_buyer_velocity": 0.0,
  "participant_quality_score_v2": 0.0,
  "status": "watching",
  "status_reason": "meets_watch_thresholds",
  "was_ever_watchlisted": true,
  "was_ever_escalated": false,
  "revival_count": 0,
  "recent_trades": [],
  "trader_wallets": [],
  "buyer_wallets": [],
  "seller_wallets": [],
  "trader_trade_counts": {},
  "buyer_trade_counts": {}
}