{
  "mint": "DN3rcQwGXQUHa9BvLe32iD8F7eEvMxdRd4WkYyEMpump",
  "symbol": "ndsh ",
  "name": "nightdash ",
  "creator_wallet": "yZvJ6tptsEQRPmoUCmvqgCwBPL2HVJY8ssLWzfyZo2X",
  "uri": "https://ipfs.io/ipfs/QmPQMUMcXNJLjra7NodzJchoA5wWD7UYJQMXv8Toqmqc3S",
  "pool": "pump",
  "bonding_curve_key": "CeVry825aAdBjst1oBdFcYJgBngyvP1HswkfQXjKQkee",
  "launch_signature": "5ThEFwJDuqxDQA7XXw9fBRKR85NbPoT4fHYWb3hyXBuoxaRDsD9JmqJ23cAgtDSt4xk9e4x59nfStcP9qYk6Bp9T",
  "created_timestamp": null,
  "first_seen_at": "2026-03-17T03:21:37.460131",
  "last_seen_at": "2026-03-17T03:30:28.895368",
  "first_trade_at": "2026-03-17T03:29:51.599101",
  "last_trade_at": "2026-03-17T03:30:28.895368",
  "last_buy_at": "2026-03-17T03:29:51.599101",
  "last_sell_at": "2026-03-17T03:30:28.895368",
  "watchlisted_at": "2026-03-17T03:21:37.460196+00:00",
  "escalated_at": null,
  "cooled_off_at": null,
  "inactive_at": null,
  "reawakened_at": null,
  "initial_buy": 34199203.154141,
  "launch_sol_amount": 0.98765432,
  "launch_market_cap_sol": 29.830218088096093,
  "current_market_cap_sol": 27.977881414323466,
  "peak_market_cap_sol": 29.830218088096093,
  "trough_market_cap_sol": 27.977881414323466,
  "peak_market_cap_at": "2026-03-17T03:21:37.460131",
  "trough_market_cap_at": "2026-03-17T03:30:28.895368",
  "total_trade_count": 2,
  "total_buy_count": 1,
  "total_sell_count": 1,
  "total_buy_sol": 9.86e-07,
  "total_sell_sol": 9.86e-07,
  "net_sol_flow": 0.0,
  "largest_buy_sol": 9.86e-07,
  "largest_sell_sol": 9.86e-07,
  "trades_last_1m": 0,
  "trades_last_5m": 0,
  "buys_last_1m": 0,
  "buys_last_5m": 0,
  "sells_last_1m": 0,
  "sells_last_5m": 0,
  "buy_sol_last_1m": 0,
  "buy_sol_last_5m": 0,
  "sell_sol_last_1m": 0,
  "sell_sol_last_5m": 0,
  "net_sol_flow_last_1m": 0,
  "net_sol_flow_last_5m": 0,
  "unique_traders": 1,
  "unique_buyers": 1,
  "unique_sellers": 1,
  "unique_traders_last_1m": 0,
  "unique_traders_last_5m": 0,
  "unique_buyers_last_1m": 0,
  "unique_buyers_last_5m": 0,
  "unique_sellers_last_1m": 0,
  "unique_sellers_last_5m": 0,
  "new_traders_last_1m": 0,
  "new_traders_last_5m": 0,
  "new_buyers_last_1m": 0,
  "new_buyers_last_5m": 0,
  "repeat_wallet_ratio": 0.0,
  "repeat_buyer_ratio": 0.0,
  "buyer_overlap_ratio": 0.0,
  "participant_churn_ratio": 0.0,
  "cluster_entropy": 0.0,
  "participant_concentration_score": 0.0,
  "wallet_novelty_score": 0.0,
  "new_buyer_velocity": 0.0,
  "participant_quality_score_v2": 0.32,
  "status": "watching",
  "status_reason": "meets_watch_thresholds",
  "was_ever_watchlisted": true,
  "was_ever_escalated": false,
  "revival_count": 0,
  "recent_trades": [
    {
      "captured_at_utc": "2026-03-17T03:29:51.599101",
      "tx_type": "buy",
      "sol_amount": 9.86e-07,
      "effective_sol_amount": 0.0,
      "is_dust_trade": true,
      "trader_wallet": "BYjoBnoCBbvEucAoLKyCUVMQohNAVHCB88xCBWzvAqn3",
      "market_cap_sol": 27.977883252782007
    },
    {
      "captured_at_utc": "2026-03-17T03:30:28.895368",
      "tx_type": "sell",
      "sol_amount": 9.86e-07,
      "effective_sol_amount": 0.0,
      "is_dust_trade": true,
      "trader_wallet": "BYjoBnoCBbvEucAoLKyCUVMQohNAVHCB88xCBWzvAqn3",
      "market_cap_sol": 27.977881414323466
    }
  ],
  "trader_wallets": [
    "BYjoBnoCBbvEucAoLKyCUVMQohNAVHCB88xCBWzvAqn3"
  ],
  "buyer_wallets": [
    "BYjoBnoCBbvEucAoLKyCUVMQohNAVHCB88xCBWzvAqn3"
  ],
  "seller_wallets": [
    "BYjoBnoCBbvEucAoLKyCUVMQohNAVHCB88xCBWzvAqn3"
  ],
  "trader_trade_counts": {
    "BYjoBnoCBbvEucAoLKyCUVMQohNAVHCB88xCBWzvAqn3": 2
  },
  "buyer_trade_counts": {
    "BYjoBnoCBbvEucAoLKyCUVMQohNAVHCB88xCBWzvAqn3": 1
  }
}