{
  "captured_at_utc": "2026-03-09T15:41:44.114035+00:00",
  "entry_count": 5,
  "archetype_breakdown": {
    "MOMENTUM_EXPANSION": 2,
    "HIGH_TIGHT_RANGE": 1,
    "FAILED_BREAKOUT": 1,
    "INSIDER_ROTATION": 1
  },
  "regime_tag_breakdown": {
    "RECYCLED_PARTICIPATION": 3,
    "RECLAIM_FRAGILE": 4,
    "SELLER_OVERHANG": 5,
    "ORGANIC_PARTICIPATION": 2,
    "THIN_LIQUIDITY": 2,
    "INSUFFICIENT_HISTORY": 3
  },
  "rows": [
    {
      "rank_mint": "64Pd4SAiQjYeZ4kwZBJE435M3umYGij9xvwPS4hgpump",
      "symbol": "Google ",
      "name": "Google Coin",
      "status": "escalated",
      "strategy_name": "momentum_expansion",
      "primary_archetype": "MOMENTUM_EXPANSION",
      "secondary_archetype": "FAILED_BREAKOUT",
      "archetype_confidence": 0.429,
      "regime_tags": [
        "RECYCLED_PARTICIPATION",
        "RECLAIM_FRAGILE",
        "SELLER_OVERHANG"
      ],
      "archetype_reasons": [
        "trade_acceleration_is_high",
        "short_term_buy_flow_is_expanding",
        "fresh_wallet_arrivals_support_momentum",
        "repeat_wallet_or_overlap_pattern_is_elevated",
        "recovery_exists_but_structure_is_still_fragile"
      ],
      "entry_bias": "momentum",
      "setup_state": "alert",
      "priority_tier": "priority",
      "confidence": "medium",
      "composite_score": 111.55,
      "tie_break_score": 115.1383,
      "current_market_cap_sol": 77.49825819931677,
      "peak_market_cap_sol": 103.88555035264308,
      "net_sol_flow_last_5m": 8.46029568,
      "buy_sol_last_5m": 20.889870619,
      "trades_last_1m": 41,
      "trades_last_5m": 41,
      "unique_buyers_last_5m": 20,
      "unique_traders_last_5m": 25,
      "participant_quality_score_v2": 0.7502,
      "wallet_novelty_score": 1.0,
      "repeat_wallet_ratio": 0.7073,
      "buyer_overlap_ratio": 0.0,
      "seller_expansion_ratio": 5.0,
      "recovery_ratio_from_trough": 0.6124,
      "mcap_stability_score": 0.6013,
      "dust_trade_share_1m": 0.0,
      "dust_trade_share_5m": 0.0,
      "entry_confirmation_score": 0.0,
      "helius_enrichment_status": "cache_throttled",
      "helius_last_error": null,
      "helius_profile_count": 3.0,
      "helius_cohort_quality_score": 0.6163,
      "helius_fresh_wallet_share": 0.0,
      "helius_sniper_wallet_share": 0.3333,
      "helius_recycled_wallet_share": 0.3333,
      "helius_funding_diversity_score": 0.6667,
      "helius_creator_shared_funder_score": 0.0,
      "risk_flags": [
        "fragile_reclaim",
        "moderate_retrace",
        "recycled_participation",
        "repeat_wallet_churn",
        "seller_overhang"
      ],
      "trigger_reasons": [
        "nonzero_initial_buy",
        "mcap_above_30",
        "mcap_above_35",
        "active_5m_trading",
        "heavy_5m_trading",
        "buy_pressure",
        "positive_5m_flow",
        "strong_positive_5m_flow",
        "multiple_recent_buyers",
        "broad_recent_participation",
        "participant_quality_v2",
        "fresh_wallet_expansion",
        "fresh_participant_wave",
        "repeat_wallet_churn",
        "already_escalated_state",
        "mcap_above_45"
      ],
      "invalidation_reasons": [
        "repeat_wallet_churn"
      ],
      "penalties": {
        "moderate_retrace": 6.0,
        "repeat_wallet_churn": 9.0,
        "recycled_participation": 4.0,
        "seller_overhang_regime": 5.0,
        "fragile_reclaim": 3.0
      },
      "quant_features": {
        "mcap_to_peak_ratio": 0.746,
        "peak_retrace_pct": 25.4003,
        "range_position_pct": 61.2396,
        "trade_acceleration_ratio": 5.0,
        "buy_acceleration_ratio": 5.0,
        "sell_acceleration_ratio": 5.0,
        "buy_pressure_ratio_5m": 0.627,
        "buy_pressure_ratio_1m": 0.627,
        "buy_sell_count_ratio_5m": 1.2778,
        "buy_sell_sol_ratio_5m": 1.6807,
        "net_flow_per_trade_5m": 0.2063,
        "net_flow_per_trade_1m": 0.2063,
        "avg_buy_size_5m": 0.9083,
        "avg_sell_size_5m": 0.6905,
        "buyer_density_5m": 0.8696,
        "seller_density_5m": 0.8333,
        "trader_participation_ratio": 0.6098,
        "buyer_participation_ratio": 0.8,
        "participation_quality_score": 0.7656,
        "microburst_ratio": 0.561,
        "flow_persistence_ratio": 5.0,
        "wash_risk_ratio": 1.64,
        "breakout_strength": 0.0,
        "wallet_novelty_score": 1.0,
        "repeat_wallet_ratio": 0.7073,
        "repeat_buyer_ratio": 0.2609,
        "buyer_overlap_ratio": 0.0,
        "same_wallet_wave_overlap_score": 0.0,
        "participant_churn_ratio": 1.0,
        "cluster_entropy": 0.9711,
        "participant_concentration_score": 0.0085,
        "new_buyer_velocity": 1.0,
        "fresh_wallet_expansion_velocity": 1.0,
        "participant_quality_score_v2": 0.7502,
        "time_since_first_seen_seconds": 9.1806,
        "time_since_last_trade_seconds": 0.0275,
        "time_since_last_buy_seconds": 0.0275,
        "time_since_last_sell_seconds": 0.0971,
        "time_since_peak_seconds": 2.4878,
        "time_since_trough_seconds": 9.1806,
        "mcap_recovery_from_trough_ratio": 0.6124,
        "recovery_ratio_from_trough": 0.6124,
        "peak_to_trough_damage_pct": 65.5318,
        "near_high_dwell_pct": 0.0,
        "revival_count": 0.0,
        "seller_expansion_ratio": 5.0,
        "buyer_refresh_ratio_1m_vs_5m": 1.0,
        "sell_absorption_score": 0.6141,
        "mcap_stability_score": 0.6013,
        "unique_buyers_last_1m": 20.0,
        "unique_buyers_last_5m": 20.0,
        "unique_traders_last_1m": 25.0,
        "unique_traders_last_5m": 25.0,
        "unique_sellers_last_1m": 15.0,
        "unique_sellers_last_5m": 15.0,
        "helius_profile_count": 3.0,
        "helius_avg_wallet_age_days": 56.9364,
        "helius_median_wallet_age_days": 2.4806,
        "helius_fresh_wallet_share": 0.0,
        "helius_sniper_wallet_share": 0.3333,
        "helius_recycled_wallet_share": 0.3333,
        "helius_high_velocity_wallet_share": 1.0,
        "helius_funding_diversity_score": 0.6667,
        "helius_top_funder_concentration_score": 0.3333,
        "helius_creator_shared_funder_score": 0.0,
        "helius_creator_wallet_age_days": 208.4627,
        "helius_creator_probable_fresh_wallet": 0.0,
        "helius_creator_probable_sniper_wallet": 0.0,
        "helius_creator_probable_recycled_wallet": 0.0,
        "helius_cohort_quality_score": 0.6163,
        "event_sequence_score": 0.0
      },
      "why_now": [
        "nonzero_initial_buy",
        "mcap_above_30",
        "mcap_above_35",
        "active_5m_trading",
        "heavy_5m_trading",
        "buy_pressure",
        "positive_5m_flow",
        "strong_positive_5m_flow"
      ],
      "rank": 1
    },
    {
      "rank_mint": "AaNKip41jSciiuZAatEkAQaFLVUehthggtFjsUDpump",
      "symbol": "eepy",
      "name": "eepy cat",
      "status": "watching",
      "strategy_name": "high_tight_range",
      "primary_archetype": "HIGH_TIGHT_RANGE",
      "secondary_archetype": "BREAKOUT_RUNNER",
      "archetype_confidence": 0.4035,
      "regime_tags": [
        "RECYCLED_PARTICIPATION",
        "RECLAIM_FRAGILE",
        "SELLER_OVERHANG"
      ],
      "archetype_reasons": [
        "token_is_compressing_close_to_highs",
        "dwell_or_stability_near_highs_is_constructive",
        "repeat_wallet_or_overlap_pattern_is_elevated",
        "recovery_exists_but_structure_is_still_fragile"
      ],
      "entry_bias": "breakout",
      "setup_state": "alert",
      "priority_tier": "priority",
      "confidence": "medium",
      "composite_score": 79.9,
      "tie_break_score": 71.7022,
      "current_market_cap_sol": 62.81464001423383,
      "peak_market_cap_sol": 66.07957647766716,
      "net_sol_flow_last_5m": 0.456430643,
      "buy_sol_last_5m": 8.33492429,
      "trades_last_1m": 35,
      "trades_last_5m": 35,
      "unique_buyers_last_5m": 14,
      "unique_traders_last_5m": 22,
      "participant_quality_score_v2": 0.7422,
      "wallet_novelty_score": 1.0,
      "repeat_wallet_ratio": 0.6571,
      "buyer_overlap_ratio": 0.0,
      "seller_expansion_ratio": 5.0,
      "recovery_ratio_from_trough": 0.9131,
      "mcap_stability_score": 0.9202,
      "dust_trade_share_1m": 0.0,
      "dust_trade_share_5m": 0.0,
      "entry_confirmation_score": 0.0,
      "helius_enrichment_status": "cache_throttled",
      "helius_last_error": null,
      "helius_profile_count": 1.0,
      "helius_cohort_quality_score": 0.716,
      "helius_fresh_wallet_share": 1.0,
      "helius_sniper_wallet_share": 0.0,
      "helius_recycled_wallet_share": 0.0,
      "helius_funding_diversity_score": 1.0,
      "helius_creator_shared_funder_score": 0.0,
      "risk_flags": [
        "fragile_reclaim",
        "recycled_participation",
        "repeat_wallet_churn",
        "seller_overhang"
      ],
      "trigger_reasons": [
        "STATUS_ESCALATED_TO_WATCHING",
        "nonzero_initial_buy",
        "mcap_above_30",
        "mcap_above_35",
        "active_5m_trading",
        "heavy_5m_trading",
        "buy_pressure",
        "multiple_recent_buyers",
        "broad_recent_participation",
        "participant_quality_v2",
        "fresh_wallet_expansion",
        "fresh_participant_wave",
        "repeat_wallet_churn",
        "mcap_above_45",
        "fast_1m_tape",
        "active_5m_tape"
      ],
      "invalidation_reasons": [
        "repeat_wallet_churn"
      ],
      "penalties": {
        "repeat_wallet_churn": 9.0,
        "seller_overhang": 6.0,
        "recycled_participation": 4.0,
        "seller_overhang_regime": 5.0,
        "fragile_reclaim": 3.0
      },
      "quant_features": {
        "mcap_to_peak_ratio": 0.9506,
        "peak_retrace_pct": 4.9409,
        "range_position_pct": 91.3087,
        "trade_acceleration_ratio": 5.0,
        "buy_acceleration_ratio": 5.0,
        "sell_acceleration_ratio": 5.0,
        "buy_pressure_ratio_5m": 0.5141,
        "buy_pressure_ratio_1m": 0.5141,
        "buy_sell_count_ratio_5m": 1.6923,
        "buy_sell_sol_ratio_5m": 1.0579,
        "net_flow_per_trade_5m": 0.013,
        "net_flow_per_trade_1m": 0.013,
        "avg_buy_size_5m": 0.3789,
        "avg_sell_size_5m": 0.606,
        "buyer_density_5m": 0.6364,
        "seller_density_5m": 0.7692,
        "trader_participation_ratio": 0.6286,
        "buyer_participation_ratio": 0.6364,
        "participation_quality_score": 0.6332,
        "microburst_ratio": 0.6286,
        "flow_persistence_ratio": 5.0,
        "wash_risk_ratio": 1.5909,
        "breakout_strength": 3.343,
        "wallet_novelty_score": 1.0,
        "repeat_wallet_ratio": 0.6571,
        "repeat_buyer_ratio": 0.6364,
        "buyer_overlap_ratio": 0.0,
        "same_wallet_wave_overlap_score": 0.0,
        "participant_churn_ratio": 1.0,
        "cluster_entropy": 0.9691,
        "participant_concentration_score": 0.0097,
        "new_buyer_velocity": 1.0,
        "fresh_wallet_expansion_velocity": 1.0,
        "participant_quality_score_v2": 0.7422,
        "time_since_first_seen_seconds": 12.9535,
        "time_since_last_trade_seconds": 0.0284,
        "time_since_last_buy_seconds": 0.0994,
        "time_since_last_sell_seconds": 0.0284,
        "time_since_peak_seconds": 2.025,
        "time_since_trough_seconds": 12.9535,
        "mcap_recovery_from_trough_ratio": 0.9131,
        "recovery_ratio_from_trough": 0.9131,
        "peak_to_trough_damage_pct": 56.849,
        "near_high_dwell_pct": 15.633,
        "revival_count": 0.0,
        "seller_expansion_ratio": 5.0,
        "buyer_refresh_ratio_1m_vs_5m": 1.0,
        "sell_absorption_score": 0.4402,
        "mcap_stability_score": 0.9202,
        "unique_buyers_last_1m": 14.0,
        "unique_buyers_last_5m": 14.0,
        "unique_traders_last_1m": 22.0,
        "unique_traders_last_5m": 22.0,
        "unique_sellers_last_1m": 10.0,
        "unique_sellers_last_5m": 10.0,
        "helius_profile_count": 1.0,
        "helius_avg_wallet_age_days": 0.0091,
        "helius_median_wallet_age_days": 0.0091,
        "helius_fresh_wallet_share": 1.0,
        "helius_sniper_wallet_share": 0.0,
        "helius_recycled_wallet_share": 0.0,
        "helius_high_velocity_wallet_share": 0.0,
        "helius_funding_diversity_score": 1.0,
        "helius_top_funder_concentration_score": 1.0,
        "helius_creator_shared_funder_score": 0.0,
        "helius_creator_wallet_age_days": 0.0,
        "helius_creator_probable_fresh_wallet": 0.0,
        "helius_creator_probable_sniper_wallet": 0.0,
        "helius_creator_probable_recycled_wallet": 0.0,
        "helius_cohort_quality_score": 0.716,
        "event_sequence_score": 0.0
      },
      "why_now": [
        "STATUS_ESCALATED_TO_WATCHING",
        "nonzero_initial_buy",
        "mcap_above_30",
        "mcap_above_35",
        "active_5m_trading",
        "heavy_5m_trading",
        "buy_pressure",
        "multiple_recent_buyers"
      ],
      "rank": 2
    },
    {
      "rank_mint": "ADs4XSdxT1wAk89qQDGgtSpfrY3XjF6VJ2jRGA9spump",
      "symbol": "cluck",
      "name": "Donald Cluck ",
      "status": "watching",
      "strategy_name": "momentum_expansion",
      "primary_archetype": "MOMENTUM_EXPANSION",
      "secondary_archetype": "FAILED_BREAKOUT",
      "archetype_confidence": 0.48,
      "regime_tags": [
        "ORGANIC_PARTICIPATION",
        "RECLAIM_FRAGILE",
        "SELLER_OVERHANG",
        "THIN_LIQUIDITY",
        "INSUFFICIENT_HISTORY"
      ],
      "archetype_reasons": [
        "trade_acceleration_is_high",
        "fresh_wallet_arrivals_support_momentum",
        "short_observation_window_favors_momentum_over_structure",
        "participant_quality_and_wallet_mix_look_organic",
        "recovery_exists_but_structure_is_still_fragile"
      ],
      "entry_bias": "momentum",
      "setup_state": "watchlist",
      "priority_tier": "watch",
      "confidence": "low",
      "composite_score": 41.05,
      "tie_break_score": 62.8077,
      "current_market_cap_sol": 43.06957097415101,
      "peak_market_cap_sol": 43.06957097415101,
      "net_sol_flow_last_5m": -1.528319383,
      "buy_sol_last_5m": 0.488888888,
      "trades_last_1m": 2,
      "trades_last_5m": 2,
      "unique_buyers_last_5m": 1,
      "unique_traders_last_5m": 2,
      "participant_quality_score_v2": 1.0,
      "wallet_novelty_score": 1.0,
      "repeat_wallet_ratio": 0.0,
      "buyer_overlap_ratio": 0.0,
      "seller_expansion_ratio": 5.0,
      "recovery_ratio_from_trough": 1.0,
      "mcap_stability_score": 1.0,
      "dust_trade_share_1m": 0.0,
      "dust_trade_share_5m": 0.0,
      "entry_confirmation_score": 0.0,
      "helius_enrichment_status": "enriched",
      "helius_last_error": null,
      "helius_profile_count": 2.0,
      "helius_cohort_quality_score": 0.572,
      "helius_fresh_wallet_share": 0.0,
      "helius_sniper_wallet_share": 0.0,
      "helius_recycled_wallet_share": 0.5,
      "helius_funding_diversity_score": 1.0,
      "helius_creator_shared_funder_score": 0.0,
      "risk_flags": [
        "fragile_reclaim",
        "insufficient_history",
        "negative_net_flow",
        "seller_overhang",
        "thin_liquidity"
      ],
      "trigger_reasons": [
        "PARTICIPANT_QUALITY_HIGH",
        "WALLET_NOVELTY_SURGE",
        "nonzero_initial_buy",
        "mcap_above_30",
        "mcap_above_35",
        "participant_quality_v2",
        "fresh_wallet_expansion",
        "high_participant_quality",
        "buyer_novelty",
        "participant_quality_event",
        "wallet_novelty",
        "wallet_novelty_event",
        "negative_sol_balance_5m",
        "trade_acceleration",
        "distributed_buyers",
        "holding_near_highs"
      ],
      "invalidation_reasons": [
        "negative_5m_flow"
      ],
      "penalties": {
        "negative_net_flow": 10.0,
        "seller_overhang": 6.0,
        "seller_overhang_regime": 5.0,
        "thin_liquidity": 3.0,
        "insufficient_history": 5.0,
        "fragile_reclaim": 3.0
      },
      "quant_features": {
        "mcap_to_peak_ratio": 1.0,
        "peak_retrace_pct": 0.0,
        "range_position_pct": 100.0,
        "trade_acceleration_ratio": 5.0,
        "buy_acceleration_ratio": 5.0,
        "sell_acceleration_ratio": 5.0,
        "buy_pressure_ratio_5m": 0.1951,
        "buy_pressure_ratio_1m": 0.1951,
        "buy_sell_count_ratio_5m": 1.0,
        "buy_sell_sol_ratio_5m": 0.2424,
        "net_flow_per_trade_5m": -0.7642,
        "net_flow_per_trade_1m": -0.7642,
        "avg_buy_size_5m": 0.4889,
        "avg_sell_size_5m": 2.0172,
        "buyer_density_5m": 1.0,
        "seller_density_5m": 1.0,
        "trader_participation_ratio": 1.0,
        "buyer_participation_ratio": 0.5,
        "participation_quality_score": 1.0,
        "microburst_ratio": 0.5,
        "flow_persistence_ratio": 0.0,
        "wash_risk_ratio": 1.0,
        "breakout_strength": 4.307,
        "wallet_novelty_score": 1.0,
        "repeat_wallet_ratio": 0.0,
        "repeat_buyer_ratio": 0.0,
        "buyer_overlap_ratio": 0.0,
        "same_wallet_wave_overlap_score": 0.0,
        "participant_churn_ratio": 1.0,
        "cluster_entropy": 1.0,
        "participant_concentration_score": 0.0,
        "new_buyer_velocity": 1.0,
        "fresh_wallet_expansion_velocity": 1.0,
        "participant_quality_score_v2": 1.0,
        "time_since_first_seen_seconds": 4.5318,
        "time_since_last_trade_seconds": 1.2685,
        "time_since_last_buy_seconds": 1.2685,
        "time_since_last_sell_seconds": 2.9571,
        "time_since_peak_seconds": 1.2685,
        "time_since_trough_seconds": 4.5318,
        "mcap_recovery_from_trough_ratio": 1.0,
        "recovery_ratio_from_trough": 1.0,
        "peak_to_trough_damage_pct": 26.2541,
        "near_high_dwell_pct": 27.9915,
        "revival_count": 0.0,
        "seller_expansion_ratio": 5.0,
        "buyer_refresh_ratio_1m_vs_5m": 1.0,
        "sell_absorption_score": 0.2949,
        "mcap_stability_score": 1.0,
        "unique_buyers_last_1m": 1.0,
        "unique_buyers_last_5m": 1.0,
        "unique_traders_last_1m": 2.0,
        "unique_traders_last_5m": 2.0,
        "unique_sellers_last_1m": 1.0,
        "unique_sellers_last_5m": 1.0,
        "helius_profile_count": 2.0,
        "helius_avg_wallet_age_days": 383.8008,
        "helius_median_wallet_age_days": 383.8008,
        "helius_fresh_wallet_share": 0.0,
        "helius_sniper_wallet_share": 0.0,
        "helius_recycled_wallet_share": 0.5,
        "helius_high_velocity_wallet_share": 1.0,
        "helius_funding_diversity_score": 1.0,
        "helius_top_funder_concentration_score": 0.5,
        "helius_creator_shared_funder_score": 0.0,
        "helius_creator_wallet_age_days": 2.3918,
        "helius_creator_probable_fresh_wallet": 0.0,
        "helius_creator_probable_sniper_wallet": 1.0,
        "helius_creator_probable_recycled_wallet": 0.0,
        "helius_cohort_quality_score": 0.572,
        "event_sequence_score": 0.55
      },
      "why_now": [
        "PARTICIPANT_QUALITY_HIGH",
        "WALLET_NOVELTY_SURGE",
        "nonzero_initial_buy",
        "mcap_above_30",
        "mcap_above_35",
        "participant_quality_v2",
        "fresh_wallet_expansion",
        "high_participant_quality"
      ],
      "rank": 3
    },
    {
      "rank_mint": "5Xvu3vhoCGZUKkv3QcMYrgrsuZzHozk479RC1f8Xpump",
      "symbol": "sleeepy",
      "name": "sleeepy cat",
      "status": "watching",
      "strategy_name": "hybrid_flow",
      "primary_archetype": "FAILED_BREAKOUT",
      "secondary_archetype": "EARLY_MICRO_PUMP",
      "archetype_confidence": 0.58,
      "regime_tags": [
        "ORGANIC_PARTICIPATION",
        "SELLER_OVERHANG",
        "INSUFFICIENT_HISTORY"
      ],
      "archetype_reasons": [
        "token_reached_breakout_context",
        "breakout_has_taken_meaningful_damage",
        "post_breakout_flow_has_weakened",
        "recovery_from_trough_is_not_good_enough",
        "participant_quality_and_wallet_mix_look_organic",
        "seller_expansion_or_sell_pressure_is_rising"
      ],
      "entry_bias": "watch_only",
      "setup_state": "watchlist",
      "priority_tier": "background",
      "confidence": "low",
      "composite_score": 7.3,
      "tie_break_score": 38.4437,
      "current_market_cap_sol": 28.333022677762667,
      "peak_market_cap_sol": 37.482498775024176,
      "net_sol_flow_last_5m": -4.699447038,
      "buy_sol_last_5m": 0.2,
      "trades_last_1m": 7,
      "trades_last_5m": 7,
      "unique_buyers_last_5m": 1,
      "unique_traders_last_5m": 7,
      "participant_quality_score_v2": 1.0,
      "wallet_novelty_score": 1.0,
      "repeat_wallet_ratio": 0.0,
      "buyer_overlap_ratio": 0.0,
      "seller_expansion_ratio": 5.0,
      "recovery_ratio_from_trough": 0.0393,
      "mcap_stability_score": 0.4992,
      "dust_trade_share_1m": 0.0,
      "dust_trade_share_5m": 0.0,
      "entry_confirmation_score": 0.0,
      "helius_enrichment_status": "cache_throttled",
      "helius_last_error": null,
      "helius_profile_count": 3.0,
      "helius_cohort_quality_score": 0.6574,
      "helius_fresh_wallet_share": 0.0,
      "helius_sniper_wallet_share": 0.0,
      "helius_recycled_wallet_share": 0.3333,
      "helius_funding_diversity_score": 0.6667,
      "helius_creator_shared_funder_score": 0.3333,
      "risk_flags": [
        "failed_breakout_structure",
        "insufficient_history",
        "moderate_retrace",
        "negative_net_flow",
        "sell_dominance",
        "seller_overhang"
      ],
      "trigger_reasons": [
        "WALLET_NOVELTY_SURGE",
        "nonzero_initial_buy",
        "active_5m_trading",
        "broad_recent_participation",
        "participant_quality_v2",
        "fresh_wallet_expansion",
        "fresh_participant_wave",
        "sell_pressure",
        "fast_1m_tape",
        "high_participant_quality",
        "buyer_novelty",
        "trader_participation",
        "wallet_novelty",
        "wallet_novelty_event",
        "sell_dominant_5m",
        "negative_sol_balance_5m"
      ],
      "invalidation_reasons": [
        "negative_5m_flow"
      ],
      "penalties": {
        "moderate_retrace": 6.0,
        "negative_net_flow": 10.0,
        "sell_dominance": 8.0,
        "seller_overhang": 6.0,
        "failed_breakout_structure": 8.0,
        "seller_overhang_regime": 5.0,
        "insufficient_history": 5.0
      },
      "quant_features": {
        "mcap_to_peak_ratio": 0.7559,
        "peak_retrace_pct": 24.41,
        "range_position_pct": 3.9274,
        "trade_acceleration_ratio": 5.0,
        "buy_acceleration_ratio": 5.0,
        "sell_acceleration_ratio": 5.0,
        "buy_pressure_ratio_5m": 0.0392,
        "buy_pressure_ratio_1m": 0.0392,
        "buy_sell_count_ratio_5m": 0.1667,
        "buy_sell_sol_ratio_5m": 0.0408,
        "net_flow_per_trade_5m": -0.6713,
        "net_flow_per_trade_1m": -0.6713,
        "avg_buy_size_5m": 0.2,
        "avg_sell_size_5m": 0.8166,
        "buyer_density_5m": 1.0,
        "seller_density_5m": 1.0,
        "trader_participation_ratio": 1.0,
        "buyer_participation_ratio": 0.1429,
        "participation_quality_score": 1.0,
        "microburst_ratio": 0.1429,
        "flow_persistence_ratio": 0.0,
        "wash_risk_ratio": 1.0,
        "breakout_strength": 0.0,
        "wallet_novelty_score": 1.0,
        "repeat_wallet_ratio": 0.0,
        "repeat_buyer_ratio": 0.0,
        "buyer_overlap_ratio": 0.0,
        "same_wallet_wave_overlap_score": 0.0,
        "participant_churn_ratio": 1.0,
        "cluster_entropy": 1.0,
        "participant_concentration_score": 0.0,
        "new_buyer_velocity": 1.0,
        "fresh_wallet_expansion_velocity": 1.0,
        "participant_quality_score_v2": 1.0,
        "time_since_first_seen_seconds": 15.2746,
        "time_since_last_trade_seconds": 0.0251,
        "time_since_last_buy_seconds": 0.0251,
        "time_since_last_sell_seconds": 0.255,
        "time_since_peak_seconds": 14.9386,
        "time_since_trough_seconds": 0.255,
        "mcap_recovery_from_trough_ratio": 0.0393,
        "recovery_ratio_from_trough": 0.0393,
        "peak_to_trough_damage_pct": 25.4079,
        "near_high_dwell_pct": 0.0,
        "revival_count": 0.0,
        "seller_expansion_ratio": 5.0,
        "buyer_refresh_ratio_1m_vs_5m": 1.0,
        "sell_absorption_score": 0.2179,
        "mcap_stability_score": 0.4992,
        "unique_buyers_last_1m": 1.0,
        "unique_buyers_last_5m": 1.0,
        "unique_traders_last_1m": 7.0,
        "unique_traders_last_5m": 7.0,
        "unique_sellers_last_1m": 6.0,
        "unique_sellers_last_5m": 6.0,
        "helius_profile_count": 3.0,
        "helius_avg_wallet_age_days": 64.9855,
        "helius_median_wallet_age_days": 11.5615,
        "helius_fresh_wallet_share": 0.0,
        "helius_sniper_wallet_share": 0.0,
        "helius_recycled_wallet_share": 0.3333,
        "helius_high_velocity_wallet_share": 1.0,
        "helius_funding_diversity_score": 0.6667,
        "helius_top_funder_concentration_score": 0.3333,
        "helius_creator_shared_funder_score": 0.3333,
        "helius_creator_wallet_age_days": 229.0904,
        "helius_creator_probable_fresh_wallet": 0.0,
        "helius_creator_probable_sniper_wallet": 0.0,
        "helius_creator_probable_recycled_wallet": 0.0,
        "helius_cohort_quality_score": 0.6574,
        "event_sequence_score": 0.55
      },
      "why_now": [
        "WALLET_NOVELTY_SURGE",
        "nonzero_initial_buy",
        "active_5m_trading",
        "broad_recent_participation",
        "participant_quality_v2",
        "fresh_wallet_expansion",
        "fresh_participant_wave",
        "sell_pressure"
      ],
      "rank": 4
    },
    {
      "rank_mint": "5R58514RiLTzXHfFKUWugCMR51RU6x9ieiGbY4jWpump",
      "symbol": "eepy",
      "name": "eepy cat",
      "status": "watching",
      "strategy_name": "breakout_continuation",
      "primary_archetype": "INSIDER_ROTATION",
      "secondary_archetype": "DEAD_LAUNCH",
      "archetype_confidence": 0.3645,
      "regime_tags": [
        "RECYCLED_PARTICIPATION",
        "RECLAIM_FRAGILE",
        "SELLER_OVERHANG",
        "THIN_LIQUIDITY",
        "INSUFFICIENT_HISTORY"
      ],
      "archetype_reasons": [
        "same_wallet_reuse_or_overlap_is_elevated",
        "wallet_base_looks_too_recycled_for_clean_expansion",
        "move_is_underdistributed_for_its_market_cap",
        "repeat_wallet_or_overlap_pattern_is_elevated",
        "recovery_exists_but_structure_is_still_fragile"
      ],
      "entry_bias": "watch_only",
      "setup_state": "research",
      "priority_tier": "background",
      "confidence": "low",
      "composite_score": 0.0,
      "tie_break_score": 1.9184,
      "current_market_cap_sol": 31.627487200095356,
      "peak_market_cap_sol": 34.136776784305475,
      "net_sol_flow_last_5m": -1.8455823869999999,
      "buy_sol_last_5m": 0,
      "trades_last_1m": 6,
      "trades_last_5m": 6,
      "unique_buyers_last_5m": 0,
      "unique_traders_last_5m": 4,
      "participant_quality_score_v2": 0.4762,
      "wallet_novelty_score": 0.0,
      "repeat_wallet_ratio": 0.6667,
      "buyer_overlap_ratio": 0.0,
      "seller_expansion_ratio": 5.0,
      "recovery_ratio_from_trough": 0.522,
      "mcap_stability_score": 0.8115,
      "dust_trade_share_1m": 0.0,
      "dust_trade_share_5m": 0.0,
      "entry_confirmation_score": 0.0,
      "helius_enrichment_status": "cache_throttled",
      "helius_last_error": null,
      "helius_profile_count": 3.0,
      "helius_cohort_quality_score": 0.7884,
      "helius_fresh_wallet_share": 0.0,
      "helius_sniper_wallet_share": 0.6667,
      "helius_recycled_wallet_share": 0.0,
      "helius_funding_diversity_score": 1.0,
      "helius_creator_shared_funder_score": 0.3333,
      "risk_flags": [
        "fragile_reclaim",
        "helius_sniper_cohort",
        "insider_rotation",
        "insufficient_history",
        "negative_net_flow",
        "recycled_participation",
        "repeat_wallet_churn",
        "sell_dominance",
        "seller_overhang",
        "thin_liquidity"
      ],
      "trigger_reasons": [
        "nonzero_initial_buy",
        "mcap_above_30",
        "active_5m_trading",
        "fresh_participant_wave",
        "sell_pressure",
        "repeat_wallet_churn",
        "fast_1m_tape",
        "sell_dominant_5m",
        "negative_sol_balance_5m",
        "trade_acceleration",
        "helius_cohort_quality",
        "mcap_stability",
        "near_high_dwell",
        "same_wallet_reuse_or_overlap_is_elevated",
        "wallet_base_looks_too_recycled_for_clean_expansion",
        "move_is_underdistributed_for_its_market_cap"
      ],
      "invalidation_reasons": [
        "insider_rotation_risk",
        "negative_5m_flow",
        "repeat_wallet_churn"
      ],
      "penalties": {
        "negative_net_flow": 10.0,
        "sell_dominance": 8.0,
        "repeat_wallet_churn": 9.0,
        "helius_sniper_cohort": 5.0,
        "seller_overhang": 6.0,
        "insider_rotation_penalty": 10.0,
        "recycled_participation": 4.0,
        "seller_overhang_regime": 5.0,
        "thin_liquidity": 3.0,
        "insufficient_history": 5.0,
        "fragile_reclaim": 3.0
      },
      "quant_features": {
        "mcap_to_peak_ratio": 0.9265,
        "peak_retrace_pct": 7.3507,
        "range_position_pct": 52.2017,
        "trade_acceleration_ratio": 5.0,
        "buy_acceleration_ratio": 0.0,
        "sell_acceleration_ratio": 5.0,
        "buy_pressure_ratio_5m": 0.0,
        "buy_pressure_ratio_1m": 0.0,
        "buy_sell_count_ratio_5m": 0.0,
        "buy_sell_sol_ratio_5m": 0.0,
        "net_flow_per_trade_5m": -0.3076,
        "net_flow_per_trade_1m": -0.3076,
        "avg_buy_size_5m": 0.0,
        "avg_sell_size_5m": 0.3076,
        "buyer_density_5m": 0.0,
        "seller_density_5m": 0.6667,
        "trader_participation_ratio": 0.6667,
        "buyer_participation_ratio": 0.0,
        "participation_quality_score": 0.2667,
        "microburst_ratio": 0.0,
        "flow_persistence_ratio": 0.0,
        "wash_risk_ratio": 1.5,
        "breakout_strength": 0.0,
        "wallet_novelty_score": 0.0,
        "repeat_wallet_ratio": 0.6667,
        "repeat_buyer_ratio": 0.0,
        "buyer_overlap_ratio": 0.0,
        "same_wallet_wave_overlap_score": 0.0,
        "participant_churn_ratio": 1.0,
        "cluster_entropy": 0.9591,
        "participant_concentration_score": 0.037,
        "new_buyer_velocity": 0.0,
        "fresh_wallet_expansion_velocity": 0.0,
        "participant_quality_score_v2": 0.4762,
        "time_since_first_seen_seconds": 7.619,
        "time_since_last_trade_seconds": 0.0268,
        "time_since_last_buy_seconds": 0.0,
        "time_since_last_sell_seconds": 0.0268,
        "time_since_peak_seconds": 7.1304,
        "time_since_trough_seconds": 7.619,
        "mcap_recovery_from_trough_ratio": 0.522,
        "recovery_ratio_from_trough": 0.522,
        "peak_to_trough_damage_pct": 15.3786,
        "near_high_dwell_pct": 93.5872,
        "revival_count": 0.0,
        "seller_expansion_ratio": 5.0,
        "buyer_refresh_ratio_1m_vs_5m": 0.0,
        "sell_absorption_score": 0.0,
        "mcap_stability_score": 0.8115,
        "unique_buyers_last_1m": 0.0,
        "unique_buyers_last_5m": 0.0,
        "unique_traders_last_1m": 4.0,
        "unique_traders_last_5m": 4.0,
        "unique_sellers_last_1m": 4.0,
        "unique_sellers_last_5m": 4.0,
        "helius_profile_count": 3.0,
        "helius_avg_wallet_age_days": 28.9116,
        "helius_median_wallet_age_days": 6.5819,
        "helius_fresh_wallet_share": 0.0,
        "helius_sniper_wallet_share": 0.6667,
        "helius_recycled_wallet_share": 0.0,
        "helius_high_velocity_wallet_share": 1.0,
        "helius_funding_diversity_score": 1.0,
        "helius_top_funder_concentration_score": 0.3333,
        "helius_creator_shared_funder_score": 0.3333,
        "helius_creator_wallet_age_days": 79.4766,
        "helius_creator_probable_fresh_wallet": 0.0,
        "helius_creator_probable_sniper_wallet": 0.0,
        "helius_creator_probable_recycled_wallet": 0.0,
        "helius_cohort_quality_score": 0.7884,
        "event_sequence_score": 0.0
      },
      "why_now": [
        "nonzero_initial_buy",
        "mcap_above_30",
        "active_5m_trading",
        "fresh_participant_wave",
        "sell_pressure",
        "repeat_wallet_churn",
        "fast_1m_tape",
        "sell_dominant_5m"
      ],
      "rank": 5
    }
  ]
}